QianduankaifaBijiben/README.md
QianduankaifaBijiben/__init__.py
QianduankaifaBijiben/__main__.py
QianduankaifaBijiben/file.epub
QianduankaifaBijiben/index.html
QianduankaifaBijiben/css/__init__.py
QianduankaifaBijiben/css/annotations.css
QianduankaifaBijiben/css/main.css
QianduankaifaBijiben/css/normalize.css
QianduankaifaBijiben/css/popup.css
QianduankaifaBijiben/font/__init__.py
QianduankaifaBijiben/font/fontello.eot
QianduankaifaBijiben/font/fontello.svg
QianduankaifaBijiben/font/fontello.ttf
QianduankaifaBijiben/font/fontello.woff
QianduankaifaBijiben/img/__init__.py
QianduankaifaBijiben/img/annotator-glyph-sprite.png
QianduankaifaBijiben/img/annotator-icon-sprite.png
QianduankaifaBijiben/img/apple-touch-icon.png
QianduankaifaBijiben/img/cancelfullscreen.png
QianduankaifaBijiben/img/close.png
QianduankaifaBijiben/img/fullscreen.png
QianduankaifaBijiben/img/loader.gif
QianduankaifaBijiben/img/menu-icon.png
QianduankaifaBijiben/img/save.png
QianduankaifaBijiben/img/saved.png
QianduankaifaBijiben/img/settings-s.png
QianduankaifaBijiben/img/settings.png
QianduankaifaBijiben/img/star.png
QianduankaifaBijiben/js/__init__.py
QianduankaifaBijiben/js/epub.js
QianduankaifaBijiben/js/epub.min.js
QianduankaifaBijiben/js/epub.min.map
QianduankaifaBijiben/js/hooks.min.js
QianduankaifaBijiben/js/hooks.min.map
QianduankaifaBijiben/js/reader.js
QianduankaifaBijiben/js/reader.js.map
QianduankaifaBijiben/js/reader.min.js
QianduankaifaBijiben/js/reader.min.map
QianduankaifaBijiben/js/hooks/__init__.py
QianduankaifaBijiben/js/hooks/extensions/__init__.py
QianduankaifaBijiben/js/hooks/extensions/highlight.js
QianduankaifaBijiben/js/libs/__init__.py
QianduankaifaBijiben/js/libs/jquery.min.js
QianduankaifaBijiben/js/libs/localforage.min.js
QianduankaifaBijiben/js/libs/screenfull.js
QianduankaifaBijiben/js/libs/screenfull.min.js
QianduankaifaBijiben/js/libs/zip.min.js
QianduankaifaBijiben/js/plugins/__init__.py
QianduankaifaBijiben/js/plugins/hypothesis.js
qianduankaifa_bijiben-2024.3.4.0.dist-info/METADATA
qianduankaifa_bijiben-2024.3.4.0.dist-info/WHEEL
qianduankaifa_bijiben-2024.3.4.0.dist-info/entry_points.txt
qianduankaifa_bijiben-2024.3.4.0.dist-info/top_level.txt
qianduankaifa_bijiben-2024.3.4.0.dist-info/RECORD
